pygtfs/__init__.py
pygtfs/_version.py
pygtfs/exceptions.py
pygtfs/feed.py
pygtfs/gtfs2db.py
pygtfs/gtfs_entities.py
pygtfs/loader.py
pygtfs/schedule.py
pygtfs/test/__init__.py
pygtfs/test/test.py
pygtfs-0.1.10.dist-info/METADATA
pygtfs-0.1.10.dist-info/WHEEL
pygtfs-0.1.10.dist-info/entry_points.txt
pygtfs-0.1.10.dist-info/top_level.txt
pygtfs-0.1.10.dist-info/RECORD
