Metadata-Version: 2.4
Name: pygtfs
Version: 0.1.10
Summary: Models GTFS data in a database.
Home-page: https://github.com/jarondl/pygtfs
Author: Yaron de Leeuw
Author-email: me@jarondl.net
License: MIT
Keywords: gtfs
Classifier: Operating System :: OS Independent
Classifier: License :: OSI Approved :: MIT License
Classifier: Programming Language :: Python :: 2
Classifier: Programming Language :: Python :: 2.7
Classifier: Programming Language :: Python :: 3
Classifier: Programming Language :: Python :: 3.6
Classifier: Programming Language :: Python :: 3.7
Classifier: Programming Language :: Python :: 3.8
Classifier: Programming Language :: Python :: 3.9
Requires-Dist: sqlalchemy>=0.7.8
Requires-Dist: pytz>=2014.9
Requires-Dist: six
Requires-Dist: docopt
Dynamic: author
Dynamic: author-email
Dynamic: classifier
Dynamic: description
Dynamic: home-page
Dynamic: keywords
Dynamic: license
Dynamic: requires-dist
Dynamic: summary
